depythel_clt/__init__.py
depythel_clt/_click_modules.py
depythel_clt/main.py
depythel_clt/py.typed
depythel-0.1.0.dist-info/entry_points.txt
depythel-0.1.0.dist-info/LICENSE
depythel-0.1.0.dist-info/WHEEL
depythel-0.1.0.dist-info/METADATA
depythel-0.1.0.dist-info/RECORD
