Metadata-Version: 2.1
Name: depythel
Version: 0.1.0
Summary: CLT for Interdependency Visualiser and Dependency Hell scrutiniser
License: GPL-3.0-or-later
Author: harens
Author-email: harensdeveloper@gmail.com
Requires-Python: >=3.7,<4.0
Classifier: License :: OSI Approved :: GNU General Public License v3 or later (GPLv3+)
Classifier: Programming Language :: Python :: 3
Classifier: Programming Language :: Python :: 3.7
Classifier: Programming Language :: Python :: 3.8
Classifier: Programming Language :: Python :: 3.9
Classifier: Programming Language :: Python :: 3.10
Requires-Dist: beartype (>=0.10.3,<0.11.0)
Requires-Dist: click (>=8.0.3,<9.0.0)
Requires-Dist: depythel_api (>=0.1.0,<0.2.0)
Requires-Dist: networkx (>=2.6.3,<3.0.0)
Requires-Dist: pyvis (>=0.1.9,<0.2.0)
Requires-Dist: rich (>=11.0.0,<12.0.0)
Requires-Dist: rich-click (>=1.2.1,<2.0.0)
